tests/__init__.py
tests/decorator_tests.py
validation_decorators/__init__.py
validation_decorators/decorators.py
validation_decorators/errors.py
validation_decorators-0.0.1.dist-info/LICENSE
validation_decorators-0.0.1.dist-info/METADATA
validation_decorators-0.0.1.dist-info/WHEEL
validation_decorators-0.0.1.dist-info/top_level.txt
validation_decorators-0.0.1.dist-info/RECORD
