Metadata-Version: 2.1
Name: validation-decorators
Version: 0.0.1
Summary: a simple, zero-dependency, easy-to-use and customizable validation and cleansing decorators for function arguments.
Home-page: https://github.com/derobertson/validation_decorators
Author: David Robertson
Author-email: derobertson89@gmail.com
License: MIT
Platform: UNKNOWN
Classifier: Programming Language :: Python :: 3
Classifier: Operating System :: OS Independent
